sagan/__init__.py
sagan/arducam.py
sagan/baro.py
sagan/board.py
sagan/i2c.py
sagan/imu.py
sagan/leds.py
sagan/rgb_ir.py
sagan/rtc.py
sagan/telemetry.py
sagan/temperature.py
sagan/uva.py
sagan-3.2.5.dist-info/METADATA
sagan-3.2.5.dist-info/WHEEL
sagan-3.2.5.dist-info/top_level.txt
sagan-3.2.5.dist-info/RECORD
