Metadata-Version: 2.1
Name: sagan
Version: 3.2.5
Summary: Python library for interfacing with sagan board
Home-page: 
Author: T A H Smith, A W Collins, Jeff Trotman
Author-email: jtrotman@dreamup.org
Requires-Dist: smbus-cffi
Requires-Dist: RPIO
